postman2py/__init__.py
postman2py/core.py
postman2py/extractors.py
postman2py-0.0.2.dist-info/LICENSE.md
postman2py-0.0.2.dist-info/METADATA
postman2py-0.0.2.dist-info/WHEEL
postman2py-0.0.2.dist-info/top_level.txt
postman2py-0.0.2.dist-info/RECORD
