Metadata-Version: 2.1
Name: postman2py
Version: 0.0.2
Summary: A library to use postman collections V2.1 in python.
Home-page: https://github.com/bodharma/postman2py
Author: Bohdan Lesiv
Author-email: boghdanlesiv@gmail.com
License: UNKNOWN
Download-URL: https://codeload.github.com/bodharma/postman2py/zip/master
Keywords: postman,rest,api
Platform: UNKNOWN
Classifier: Programming Language :: Python :: 3
Classifier: License :: OSI Approved :: GNU General Public License v3 (GPLv3)
Classifier: Operating System :: OS Independent
Requires-Python: >=3.6
Requires-Dist: requests
Requires-Dist: python-magic
Requires-Dist: loguru
